.gitignore
CHANGELOG.md
DEVELOP.md
Dockerfile
LICENSE.txt
Makefile
README.md
RELEASE.md
environment.yml
pyproject.toml
requirements-package.txt
requirements.txt
setup.cfg
setup.py
.github/workflows/test.yml
examples/iris.ipynb
examples/mnist.ipynb
tsne/__init__.py
tsne/_bh_sne.py
tsne/_generated_version.py
tsne/bh_sne.pyx
tsne.egg-info/PKG-INFO
tsne.egg-info/SOURCES.txt
tsne.egg-info/dependency_links.txt
tsne.egg-info/not-zip-safe
tsne.egg-info/requires.txt
tsne.egg-info/top_level.txt
tsne/includes/bh_tsne/LICENSE
tsne/includes/bh_tsne/Readme.txt
tsne/includes/bh_tsne/compile_linux
tsne/includes/bh_tsne/compile_mac
tsne/includes/bh_tsne/fast_tsne.m
tsne/includes/bh_tsne/quadtree.cpp
tsne/includes/bh_tsne/quadtree.h
tsne/includes/bh_tsne/tsne.cpp
tsne/includes/bh_tsne/tsne.h
tsne/includes/bh_tsne/vptree.h
tsne/tests/__init__.py
tsne/tests/test_import.py
tsne/tests/test_iris.py
tsne/tests/test_seed.py