Metadata-Version: 2.1
Name: tsne
Version: 0.3.1
Summary: TSNE algorithms
Home-page: https://github.com/danielfrg/tsne
Maintainer: Daniel Rodriguez
Maintainer-email: daniel@danielfrg.com
License: Apache License, Version 2.0
Keywords: TSNE,algorithms,numpy,cython
Platform: UNKNOWN
Classifier: License :: OSI Approved :: Apache Software License
Classifier: Programming Language :: Python :: 3.6
Classifier: Programming Language :: Python :: 3.7
Classifier: Programming Language :: Python :: 3.8
Requires-Python: >=3.6
Provides-Extra: test
Provides-Extra: dev
